{
  "modelGlbPath": "/Users/dog/Desktop/铭润/output/debug_v5/qihang_product_pearl_phase2_10986dc.glb",
  "modelGlbSha256": "2011112cdb09278d2967cabc8e1b123a65417dc3614a3eeab704f88cd7d3ef58",
  "asset": {
    "generator": "Khronos glTF Blender I/O v5.0.21",
    "version": "2.0"
  },
  "counts": {
    "scenes": 1,
    "nodes": 85,
    "meshes": 38,
    "materials": 21,
    "bufferViews": 151,
    "accessors": 151,
    "animations": 0,
    "binBytes": 3626092
  },
  "sceneRoots": [
    "QIHANG_Product"
  ],
  "requiredNodeSummaries": {
    "QIHANG_Product": {
      "index": 82,
      "parent": null,
      "children": [
        "Case_Base",
        "Case_Lid_Pivot"
      ],
      "mesh": null,
      "translation": [
        0.0,
        0.01,
        0.0
      ],
      "rotation": [],
      "scale": [
        225.28181458,
        225.28181458,
        225.28181458
      ],
      "productLocalOriginMm": [
        0.0,
        0.0,
        0.0
      ]
    },
    "Case_Base": {
      "index": 70,
      "parent": "QIHANG_Product",
      "children": [
        "Base_Pivot_Assembly",
        "Brooch_Camera",
        "Case_Base_Shell",
        "DockWell_L",
        "DockWell_R",
        "Earbud_Left",
        "Earbud_Right",
        "Case_Base_Platform_V4",
        "Case_Base_Arc_Ramp_V4"
      ],
      "mesh": null,
      "translation": [
        0.0,
        0.0,
        0.0
      ],
      "rotation": [
        0.0,
        0.70710678,
        0.0,
        0.70710678
      ],
      "scale": [],
      "productLocalOriginMm": [
        0.0,
        0.0,
        0.0
      ]
    },
    "Case_Lid": {
      "index": 80,
      "parent": "Case_Lid_Pivot",
      "children": [
        "Case_Lid_Shell",
        "Lid_Pivot_Assembly",
        "Lid_Pivot_Hole_Center",
        "Lid_Pivot_Snap_Lip",
        "Pivot_Plug_Guide_Anchor",
        "Pivot_Plug_Hover_Anchor",
        "Pivot_Plug_Seat_Anchor"
      ],
      "mesh": null,
      "translation": [
        0.0,
        0.00456456,
        0.0334
      ],
      "rotation": [],
      "scale": [],
      "productLocalOriginMm": [
        0.0,
        14.829,
        0.0
      ]
    },
    "Case_Lid_Pivot": {
      "index": 81,
      "parent": "QIHANG_Product",
      "children": [
        "Case_Lid"
      ],
      "mesh": null,
      "translation": [
        -0.0334,
        0.01026441,
        -0.0
      ],
      "rotation": [
        0.0,
        0.70710678,
        0.0,
        0.70710678
      ],
      "scale": [],
      "productLocalOriginMm": [
        -33.4,
        10.2644,
        -0.0
      ]
    },
    "Case_Base_Shell": {
      "index": 29,
      "parent": "Case_Base",
      "children": [],
      "mesh": 19,
      "translation": [],
      "rotation": [],
      "scale": [
        0.88,
        0.92000002,
        0.88
      ],
      "productLocalOriginMm": [
        0.0,
        0.0,
        0.0
      ]
    },
    "Case_Lid_Shell": {
      "index": 71,
      "parent": "Case_Lid",
      "children": [],
      "mesh": 33,
      "translation": [],
      "rotation": [],
      "scale": [
        0.88,
        0.92000002,
        0.88
      ],
      "productLocalOriginMm": [
        0.0,
        14.829,
        0.0
      ]
    },
    "Earbud_Left": {
      "index": 50,
      "parent": "Case_Base",
      "children": [
        "Earbud_Left_NozzleAnchor",
        "GLB_Ear_Left"
      ],
      "mesh": null,
      "translation": [
        0.00115,
        0.0039,
        -0.0105
      ],
      "rotation": [
        -0.70710678,
        0.0,
        -0.0,
        0.70710678
      ],
      "scale": [
        2.33999991,
        2.33999991,
        2.33999991
      ],
      "productLocalOriginMm": [
        -10.5,
        3.9,
        -1.15
      ]
    },
    "Earbud_Right": {
      "index": 69,
      "parent": "Case_Base",
      "children": [
        "Earbud_Right_NozzleAnchor",
        "GLB_Ear_Right"
      ],
      "mesh": null,
      "translation": [
        -0.00045,
        0.0034,
        0.0087
      ],
      "rotation": [
        -0.70710678,
        -0.0,
        0.0,
        0.70710678
      ],
      "scale": [
        2.33999991,
        2.33999991,
        2.33999991
      ],
      "productLocalOriginMm": [
        8.7,
        3.4,
        0.45
      ]
    },
    "Brooch_Camera": {
      "index": 28,
      "parent": "Case_Base",
      "children": [
        "GLB_Camera"
      ],
      "mesh": null,
      "translation": [
        -0.00095,
        0.0024,
        0.0288
      ],
      "rotation": [],
      "scale": [
        1.73999989,
        1.73999989,
        1.73999989
      ],
      "productLocalOriginMm": [
        28.8,
        2.4,
        0.95
      ]
    },
    "Pivot_Pin_Printable": {
      "index": 2,
      "parent": "Pivot_Module_Pin",
      "children": [],
      "mesh": 1,
      "translation": [
        0.0,
        0.010625,
        -0.0334
      ],
      "rotation": [],
      "scale": [],
      "productLocalOriginMm": [
        -33.4,
        10.625,
        -0.0
      ]
    },
    "Lid_Pivot_Hole_Center": {
      "index": 75,
      "parent": "Case_Lid",
      "children": [],
      "mesh": null,
      "translation": [
        0.0,
        -0.00420397,
        -0.0334
      ],
      "rotation": [],
      "scale": [],
      "productLocalOriginMm": [
        -33.4,
        10.625,
        -0.0
      ]
    },
    "DockWell_L": {
      "index": 30,
      "parent": "Case_Base",
      "children": [],
      "mesh": null,
      "translation": [
        0.00115,
        0.0078,
        -0.0105
      ],
      "rotation": [],
      "scale": [],
      "productLocalOriginMm": [
        -10.5,
        7.8,
        -1.15
      ]
    },
    "DockWell_R": {
      "index": 31,
      "parent": "Case_Base",
      "children": [],
      "mesh": null,
      "translation": [
        -0.00045,
        0.0071,
        0.0087
      ],
      "rotation": [],
      "scale": [],
      "productLocalOriginMm": [
        8.7,
        7.1,
        0.45
      ]
    }
  },
  "partBoundingBoxes": {
    "Case_Base_Shell": {
      "bboxMinMm": [
        -43.744,
        -12.2034,
        -17.0
      ],
      "bboxMaxMm": [
        43.7257,
        9.4137,
        17.0
      ],
      "bboxSizeMm": [
        87.4697,
        21.6171,
        34.0
      ],
      "bboxCenterMm": [
        -0.0091,
        -1.3949,
        0.0
      ]
    },
    "Case_Lid_Shell": {
      "bboxMinMm": [
        -42.944,
        8.7117,
        -16.2
      ],
      "bboxMaxMm": [
        42.944,
        18.8356,
        16.2
      ],
      "bboxSizeMm": [
        85.888,
        10.1239,
        32.4
      ],
      "bboxCenterMm": [
        0.0,
        13.7736,
        0.0
      ]
    },
    "Earbud_Left": {
      "bboxMinMm": [
        -14.8369,
        -0.74,
        -6.1079
      ],
      "bboxMaxMm": [
        -0.5042,
        8.54,
        4.006
      ],
      "bboxSizeMm": [
        14.3327,
        9.2799,
        10.1139
      ],
      "bboxCenterMm": [
        -7.6706,
        3.9,
        -1.0509
      ]
    },
    "Earbud_Right": {
      "bboxMinMm": [
        4.3631,
        -1.24,
        -4.706
      ],
      "bboxMaxMm": [
        18.6958,
        8.04,
        5.4079
      ],
      "bboxSizeMm": [
        14.3327,
        9.2799,
        10.1139
      ],
      "bboxCenterMm": [
        11.5294,
        3.4,
        0.3509
      ]
    },
    "Brooch_Camera": {
      "bboxMinMm": [
        25.5888,
        -4.8108,
        -1.9082
      ],
      "bboxMaxMm": [
        31.865,
        1.4467,
        3.8082
      ],
      "bboxSizeMm": [
        6.2762,
        6.2575,
        5.7165
      ],
      "bboxCenterMm": [
        28.7269,
        -1.682,
        0.95
      ]
    },
    "Pivot_Pin_Printable": {
      "bboxMinMm": [
        -38.875,
        9.705,
        -5.475
      ],
      "bboxMaxMm": [
        -27.925,
        16.745,
        5.475
      ],
      "bboxSizeMm": [
        10.95,
        7.04,
        10.95
      ],
      "bboxCenterMm": [
        -33.4,
        13.225,
        -0.0
      ]
    }
  },
  "hierarchyGuards": {
    "QIHANG_Product_children": [
      "Case_Base",
      "Case_Lid_Pivot"
    ],
    "Case_Base_children": [
      "Base_Pivot_Assembly",
      "Brooch_Camera",
      "Case_Base_Shell",
      "DockWell_L",
      "DockWell_R",
      "Earbud_Left",
      "Earbud_Right",
      "Case_Base_Platform_V4",
      "Case_Base_Arc_Ramp_V4"
    ],
    "Case_Lid_Pivot_children": [
      "Case_Lid"
    ],
    "Case_Lid_children": [
      "Case_Lid_Shell",
      "Lid_Pivot_Assembly",
      "Lid_Pivot_Hole_Center",
      "Lid_Pivot_Snap_Lip",
      "Pivot_Plug_Guide_Anchor",
      "Pivot_Plug_Hover_Anchor",
      "Pivot_Plug_Seat_Anchor"
    ]
  },
  "sourceInputPath": "output/debug_v4/qihang_product_pearl_phase3.glb",
  "sourceInputSha256": "fd274c48530a893621ae236262aa8a3a31ff7e00bd1ed8a6014eb834dcb1d900",
  "outputSha256": "2011112cdb09278d2967cabc8e1b123a65417dc3614a3eeab704f88cd7d3ef58",
  "phase": 2,
  "phaseName": "open_front_window_and_rebuild_sidewalls",
  "phaseLogs": [
    {
      "phase": 1,
      "name": "baseline_six_view_diagnostics",
      "geometryModified": false,
      "diagnosticSheetPath": "output/debug_v5/qihang_product_pearl_phase1_six_views.png",
      "candidateSummary": {
        "heuristicName": "vertical_inner_wall_strip",
        "xRangeMm": [
          6.0,
          36.0
        ],
        "yRangeMm": [
          -0.6,
          9.35
        ],
        "absZRangeMm": [
          13.0,
          16.25
        ],
        "normalZAbsMin": 0.7,
        "normalYAbsMax": 0.3,
        "positiveZ": {
          "componentCount": 1,
          "triangleCount": 33,
          "components": [
            {
              "triangleIndices": [
                1797,
                1799,
                1815,
                1817,
                1833,
                1835,
                1851,
                1853,
                1869,
                1871,
                1887,
                1889,
                1905,
                1907,
                1923,
                1925,
                1941,
                1943,
                1959,
                1961,
                1977,
                1979,
                1995,
                1997,
                2013,
                2015,
                2031,
                2033,
                2049,
                2051,
                2067,
                2069,
                2085
              ],
              "triangleCount": 33,
              "bboxMinProductMm": [
                6.0491,
                -0.4561,
                13.3779
              ],
              "bboxMaxProductMm": [
                35.7066,
                9.25,
                16.2
              ],
              "bboxSizeProductMm": [
                29.6575,
                9.7061,
                2.8221
              ],
              "averageNormal": [
                -0.0995,
                -0.098,
                -0.9777
              ]
            }
          ]
        },
        "negativeZ": {
          "componentCount": 0,
          "triangleCount": 0,
          "components": []
        }
      }
    },
    {
      "phase": 2,
      "name": "open_front_window_and_rebuild_sidewalls",
      "geometryModified": true,
      "diagnosticSheetPath": "/Users/dog/Desktop/铭润/output/debug_v5/qihang_product_pearl_phase2_10986dc_six_views.png",
      "rebuildChangeLog": {
        "node": "Case_Base_Shell",
        "operation": "delete_front_blocker_and_rebuild_front_window_with_structured_patch",
        "blockerRemovedTriangleCount": 86,
        "afterBlockerTriangleCount": 2474,
        "frontFaceRemovedTriangleCount": 2,
        "afterFrontFaceTriangleCount": 2472,
        "sidewallRemovedTriangleCount": 2,
        "afterSidewallTriangleCount": 2470,
        "fillPatchTriangleCount": 34,
        "finalTriangleCount": 2504,
        "boundaryVertexCountBeforeFill": 36,
        "boundaryEdgeCountAfterFill": 0,
        "blockerComponent": {
          "triangleIndices": [
            608,
            609,
            610,
            611,
            626,
            627,
            628,
            629,
            644,
            645,
            646,
            647,
            662,
            663,
            664,
            665,
            680,
            681,
            682,
            683,
            698,
            699,
            700,
            701,
            716,
            717,
            718,
            719,
            734,
            735,
            736,
            737,
            752,
            753,
            754,
            755,
            770,
            771,
            772,
            773,
            788,
            789,
            790,
            791,
            806,
            807,
            808,
            809,
            824,
            825,
            826,
            827,
            842,
            843,
            844,
            845,
            2370,
            2371,
            2372,
            2373,
            2374,
            2375,
            2376,
            2377,
            2378,
            2379,
            2380,
            2381,
            2382,
            2383,
            2384,
            2385,
            2386,
            2387,
            2388,
            2389,
            2390,
            2391,
            2392,
            2393,
            2394,
            2395,
            2396,
            2397,
            2398,
            2399
          ],
          "triangleCount": 86,
          "bboxMinProductMm": [
            -29.3323,
            -0.458,
            -17.0
          ],
          "bboxMaxProductMm": [
            -1.9367,
            9.3501,
            -14.8097
          ],
          "bboxSizeProductMm": [
            27.3956,
            9.8081,
            2.1903
          ],
          "averageNormal": [
            0.0015,
            0.3474,
            0.0301
          ],
          "seedRangesMm": {
            "x": [
              -29.0,
              -1.8
            ],
            "y": [
              -0.6,
              9.5
            ],
            "z": [
              -17.1,
              -15.0
            ]
          },
          "allowedRangesMm": {
            "x": [
              -30.0,
              -1.0
            ],
            "y": [
              -1.0,
              10.0
            ],
            "z": [
              -17.5,
              -14.5
            ]
          }
        },
        "frontFaceComponent": {
          "triangleIndices": [
            592,
            593
          ],
          "triangleCount": 2,
          "bboxMinProductMm": [
            -2.1072,
            -0.95,
            -16.9958
          ],
          "bboxMaxProductMm": [
            0.2643,
            9.3025,
            -15.5505
          ],
          "bboxSizeProductMm": [
            2.3715,
            10.2525,
            1.4453
          ],
          "selectionCenterRangesMm": {
            "x": [
              -1.6,
              -1.0
            ],
            "y": [
              -1.0,
              10.0
            ],
            "z": [
              -16.7,
              -15.5
            ]
          },
          "normalZAbsMin": 0.9,
          "aspectRatioMin": 4.0
        },
        "sidewallComponent": {
          "triangleIndices": [
            2310,
            2311
          ],
          "triangleCount": 2,
          "bboxMinProductMm": [
            -2.0229,
            -0.95,
            -16.3441
          ],
          "bboxMaxProductMm": [
            0.2643,
            9.3025,
            -15.5505
          ],
          "bboxSizeProductMm": [
            2.2872,
            10.2525,
            0.7936
          ],
          "selectionCenterRangesMm": {
            "x": [
              -2.5,
              0.5
            ],
            "y": [
              -1.0,
              10.0
            ],
            "z": [
              -16.6,
              -15.3
            ]
          },
          "normalXMin": 0.8,
          "areaMm2Min": 1.0
        },
        "fillPatchDebug": {
          "boundaryVertexCount": 36,
          "outerStripVertexCount": 16,
          "innerStripVertexCount": 15,
          "stripTriangleCount": 29,
          "leftCapTriangleCount": 4,
          "rightCapTriangleCount": 1,
          "outerStripSlice": [
            2,
            18
          ],
          "innerStripSlice": [
            19,
            34
          ],
          "leftCapLoopIndices": [
            35,
            0,
            1,
            2,
            33,
            34
          ],
          "rightCapLoopIndices": [
            17,
            18,
            19
          ],
          "patchBboxMinProductMm": [
            -29.3323,
            -0.95,
            -17.0
          ],
          "patchBboxMaxProductMm": [
            0.2643,
            9.3501,
            -14.8097
          ],
          "patchBboxSizeProductMm": [
            29.5966,
            10.3001,
            2.1903
          ],
          "stripBboxMinProductMm": [
            -28.9333,
            -0.7904,
            -17.0
          ],
          "stripBboxMaxProductMm": [
            0.2643,
            -0.4561,
            -16.0639
          ],
          "stripBboxSizeProductMm": [
            29.1977,
            0.3343,
            0.9361
          ],
          "leftCapBboxMinProductMm": [
            -29.3323,
            -0.4564,
            -16.8584
          ],
          "leftCapBboxMaxProductMm": [
            -27.6859,
            9.3501,
            -14.8097
          ],
          "leftCapBboxSizeProductMm": [
            1.6465,
            9.8065,
            2.0486
          ],
          "rightCapBboxMinProductMm": [
            -2.1072,
            -0.95,
            -16.29
          ],
          "rightCapBboxMaxProductMm": [
            0.2643,
            -0.4561,
            -15.552
          ],
          "rightCapBboxSizeProductMm": [
            2.3715,
            0.4939,
            0.738
          ]
        },
        "fillPatchBboxMinProductMm": [
          -29.3323,
          -0.95,
          -17.0
        ],
        "fillPatchBboxMaxProductMm": [
          0.2643,
          9.3501,
          -14.8097
        ],
        "fillPatchBboxSizeProductMm": [
          29.5966,
          10.3001,
          2.1903
        ]
      },
      "postRebuildCandidateSummary": {
        "heuristicName": "vertical_inner_wall_strip",
        "xRangeMm": [
          6.0,
          36.0
        ],
        "yRangeMm": [
          -0.6,
          9.35
        ],
        "absZRangeMm": [
          13.0,
          16.25
        ],
        "normalZAbsMin": 0.7,
        "normalYAbsMax": 0.3,
        "positiveZ": {
          "componentCount": 1,
          "triangleCount": 33,
          "components": [
            {
              "triangleIndices": [
                1739,
                1741,
                1757,
                1759,
                1775,
                1777,
                1793,
                1795,
                1811,
                1813,
                1829,
                1831,
                1847,
                1849,
                1865,
                1867,
                1883,
                1885,
                1901,
                1903,
                1919,
                1921,
                1937,
                1939,
                1955,
                1957,
                1973,
                1975,
                1991,
                1993,
                2009,
                2011,
                2027
              ],
              "triangleCount": 33,
              "bboxMinProductMm": [
                6.0491,
                -0.4561,
                13.3779
              ],
              "bboxMaxProductMm": [
                35.7066,
                9.25,
                16.2
              ],
              "bboxSizeProductMm": [
                29.6575,
                9.7061,
                2.8221
              ],
              "averageNormal": [
                -0.0995,
                -0.098,
                -0.9777
              ]
            }
          ]
        },
        "negativeZ": {
          "componentCount": 0,
          "triangleCount": 0,
          "components": []
        }
      }
    }
  ],
  "diagnosticSheetPath": "/Users/dog/Desktop/铭润/output/debug_v5/qihang_product_pearl_phase2_10986dc_six_views.png",
  "phase1DiagnosticSheetPath": "output/debug_v5/qihang_product_pearl_phase1_six_views.png"
}
